[
  {
    "arabic_text": "\u0642\u064f\u0644\u0652",
    "arabic_plain": "\u0642\u0644",
    "transliteration": "qul",
    "english_meaning": "Say",
    "root_word": "\u0642\u0648\u0644",
    "surah_number": 112,
    "ayah_number": 1,
    "word_position": 1,
    "quran_frequency": 332,
    "min_phase": 5,
    "difficulty_tier": 2,
    "prerequisite_letter_ids": [21, 23],
    "prerequisite_symbols": ["damma", "sukoon"],
    "suitable_types": ["buildup", "free_reading"],
    "skill_buckets": ["connected_decoding"],
    "letter_breakdown": [
      { "letter_id": 21, "position": "initial", "diacritical": "damma", "tajweed_rules": [] },
      { "letter_id": 23, "position": "final", "diacritical": "sukoon", "tajweed_rules": [] }
    ]
  },
  {
    "arabic_text": "\u0647\u064f\u0648\u064e",
    "arabic_plain": "\u0647\u0648",
    "transliteration": "huwa",
    "english_meaning": "He is",
    "root_word": null,
    "surah_number": 112,
    "ayah_number": 1,
    "word_position": 2,
    "quran_frequency": 1000,
    "min_phase": 5,
    "difficulty_tier": 1,
    "prerequisite_letter_ids": [26, 27],
    "prerequisite_symbols": ["damma", "fatha"],
    "suitable_types": ["buildup", "free_reading"],
    "skill_buckets": ["connected_decoding"],
    "letter_breakdown": [
      { "letter_id": 26, "position": "initial", "diacritical": "damma", "tajweed_rules": [] },
      { "letter_id": 27, "position": "final", "diacritical": "fatha", "tajweed_rules": [] }
    ]
  },
  {
    "arabic_text": "\u0627\u0644\u0644\u0651\u064e\u0647\u064f",
    "arabic_plain": "\u0627\u0644\u0644\u0647",
    "transliteration": "allahu",
    "english_meaning": "Allah",
    "root_word": null,
    "surah_number": 112,
    "ayah_number": 1,
    "word_position": 3,
    "quran_frequency": 2699,
    "min_phase": 6,
    "difficulty_tier": 3,
    "prerequisite_letter_ids": [1, 23, 26],
    "prerequisite_symbols": ["shaddah", "fatha", "damma"],
    "suitable_types": ["free_reading"],
    "skill_buckets": ["connected_decoding", "al_recognition"],
    "letter_breakdown": [
      { "letter_id": 1, "position": "initial", "diacritical": null, "tajweed_rules": ["alif_lam"] },
      { "letter_id": 23, "position": "medial", "diacritical": null, "tajweed_rules": ["alif_lam"] },
      { "letter_id": 23, "position": "medial", "diacritical": "shaddah_fatha", "tajweed_rules": ["shaddah"] },
      { "letter_id": 26, "position": "final", "diacritical": "damma", "tajweed_rules": [] }
    ]
  },
  {
    "arabic_text": "\u0623\u064e\u062d\u064e\u062f\u064c",
    "arabic_plain": "\u0627\u062d\u062f",
    "transliteration": "ahadun",
    "english_meaning": "One",
    "root_word": "\u0627\u062d\u062f",
    "surah_number": 112,
    "ayah_number": 1,
    "word_position": 4,
    "quran_frequency": 86,
    "min_phase": 6,
    "difficulty_tier": 3,
    "prerequisite_letter_ids": [1, 6, 8],
    "prerequisite_symbols": ["fatha", "tanwin_damm", "hamzah"],
    "suitable_types": ["free_reading"],
    "skill_buckets": ["connected_decoding", "hamzah_reading"],
    "letter_breakdown": [
      { "letter_id": 1, "position": "initial", "diacritical": "fatha", "tajweed_rules": ["hamzah_above"] },
      { "letter_id": 6, "position": "medial", "diacritical": "fatha", "tajweed_rules": [] },
      { "letter_id": 8, "position": "final", "diacritical": "tanwin_damm", "tajweed_rules": [] }
    ]
  },
  {
    "arabic_text": "\u0627\u0644\u0644\u0651\u064e\u0647\u064f",
    "arabic_plain": "\u0627\u0644\u0644\u0647",
    "transliteration": "allahu",
    "english_meaning": "Allah",
    "root_word": null,
    "surah_number": 112,
    "ayah_number": 2,
    "word_position": 1,
    "quran_frequency": 2699,
    "min_phase": 6,
    "difficulty_tier": 3,
    "prerequisite_letter_ids": [1, 23, 26],
    "prerequisite_symbols": ["shaddah", "fatha", "damma"],
    "suitable_types": ["free_reading"],
    "skill_buckets": ["connected_decoding", "al_recognition"],
    "letter_breakdown": [
      { "letter_id": 1, "position": "initial", "diacritical": null, "tajweed_rules": ["alif_lam"] },
      { "letter_id": 23, "position": "medial", "diacritical": null, "tajweed_rules": ["alif_lam"] },
      { "letter_id": 23, "position": "medial", "diacritical": "shaddah_fatha", "tajweed_rules": ["shaddah"] },
      { "letter_id": 26, "position": "final", "diacritical": "damma", "tajweed_rules": [] }
    ]
  },
  {
    "arabic_text": "\u0627\u0644\u0635\u0651\u064e\u0645\u064e\u062f\u064f",
    "arabic_plain": "\u0627\u0644\u0635\u0645\u062f",
    "transliteration": "assamadu",
    "english_meaning": "The Eternal Refuge",
    "root_word": "\u0635\u0645\u062f",
    "surah_number": 112,
    "ayah_number": 2,
    "word_position": 2,
    "quran_frequency": 1,
    "min_phase": 6,
    "difficulty_tier": 4,
    "prerequisite_letter_ids": [1, 23, 14, 24, 8],
    "prerequisite_symbols": ["sukoon", "shaddah", "fatha", "damma"],
    "suitable_types": ["free_reading"],
    "skill_buckets": ["connected_decoding", "al_recognition", "emphatic_letters"],
    "letter_breakdown": [
      { "letter_id": 1, "position": "initial", "diacritical": null, "tajweed_rules": ["alif_lam_shamsiyyah"] },
      { "letter_id": 23, "position": "medial", "diacritical": "sukoon", "tajweed_rules": ["alif_lam_shamsiyyah"] },
      { "letter_id": 14, "position": "medial", "diacritical": "shaddah_fatha", "tajweed_rules": ["shaddah"] },
      { "letter_id": 24, "position": "medial", "diacritical": "fatha", "tajweed_rules": [] },
      { "letter_id": 8, "position": "final", "diacritical": "damma", "tajweed_rules": [] }
    ]
  },
  {
    "arabic_text": "\u0644\u064e\u0645\u0652",
    "arabic_plain": "\u0644\u0645",
    "transliteration": "lam",
    "english_meaning": "Not",
    "root_word": null,
    "surah_number": 112,
    "ayah_number": 3,
    "word_position": 1,
    "quran_frequency": 1550,
    "min_phase": 5,
    "difficulty_tier": 1,
    "prerequisite_letter_ids": [23, 24],
    "prerequisite_symbols": ["fatha", "sukoon"],
    "suitable_types": ["buildup", "free_reading"],
    "skill_buckets": ["connected_decoding"],
    "letter_breakdown": [
      { "letter_id": 23, "position": "initial", "diacritical": "fatha", "tajweed_rules": [] },
      { "letter_id": 24, "position": "final", "diacritical": "sukoon", "tajweed_rules": [] }
    ]
  },
  {
    "arabic_text": "\u064a\u064e\u0644\u0650\u062f\u0652",
    "arabic_plain": "\u064a\u0644\u062f",
    "transliteration": "yalid",
    "english_meaning": "He begets",
    "root_word": "\u0648\u0644\u062f",
    "surah_number": 112,
    "ayah_number": 3,
    "word_position": 2,
    "quran_frequency": 18,
    "min_phase": 5,
    "difficulty_tier": 2,
    "prerequisite_letter_ids": [28, 23, 8],
    "prerequisite_symbols": ["fatha", "kasra", "sukoon"],
    "suitable_types": ["buildup", "free_reading"],
    "skill_buckets": ["connected_decoding"],
    "letter_breakdown": [
      { "letter_id": 28, "position": "initial", "diacritical": "fatha", "tajweed_rules": [] },
      { "letter_id": 23, "position": "medial", "diacritical": "kasra", "tajweed_rules": [] },
      { "letter_id": 8, "position": "final", "diacritical": "sukoon", "tajweed_rules": [] }
    ]
  },
  {
    "arabic_text": "\u0648\u064e\u0644\u064e\u0645\u0652",
    "arabic_plain": "\u0648\u0644\u0645",
    "transliteration": "walam",
    "english_meaning": "And not",
    "root_word": null,
    "surah_number": 112,
    "ayah_number": 3,
    "word_position": 3,
    "quran_frequency": 400,
    "min_phase": 5,
    "difficulty_tier": 1,
    "prerequisite_letter_ids": [27, 23, 24],
    "prerequisite_symbols": ["fatha", "sukoon"],
    "suitable_types": ["buildup", "free_reading"],
    "skill_buckets": ["connected_decoding"],
    "letter_breakdown": [
      { "letter_id": 27, "position": "initial", "diacritical": "fatha", "tajweed_rules": [] },
      { "letter_id": 23, "position": "medial", "diacritical": "fatha", "tajweed_rules": [] },
      { "letter_id": 24, "position": "final", "diacritical": "sukoon", "tajweed_rules": [] }
    ]
  },
  {
    "arabic_text": "\u064a\u064f\u0648\u0644\u064e\u062f\u0652",
    "arabic_plain": "\u064a\u0648\u0644\u062f",
    "transliteration": "yulad",
    "english_meaning": "He is begotten",
    "root_word": "\u0648\u0644\u062f",
    "surah_number": 112,
    "ayah_number": 3,
    "word_position": 4,
    "quran_frequency": 18,
    "min_phase": 6,
    "difficulty_tier": 3,
    "prerequisite_letter_ids": [28, 27, 23, 8],
    "prerequisite_symbols": ["damma", "fatha", "sukoon"],
    "suitable_types": ["free_reading"],
    "skill_buckets": ["connected_decoding", "madd_reading"],
    "letter_breakdown": [
      { "letter_id": 28, "position": "initial", "diacritical": "damma", "tajweed_rules": [] },
      { "letter_id": 27, "position": "medial", "diacritical": null, "tajweed_rules": ["madd"] },
      { "letter_id": 23, "position": "medial", "diacritical": "fatha", "tajweed_rules": [] },
      { "letter_id": 8, "position": "final", "diacritical": "sukoon", "tajweed_rules": [] }
    ]
  },
  {
    "arabic_text": "\u0648\u064e\u0644\u064e\u0645\u0652",
    "arabic_plain": "\u0648\u0644\u0645",
    "transliteration": "walam",
    "english_meaning": "And not",
    "root_word": null,
    "surah_number": 112,
    "ayah_number": 4,
    "word_position": 1,
    "quran_frequency": 400,
    "min_phase": 5,
    "difficulty_tier": 1,
    "prerequisite_letter_ids": [27, 23, 24],
    "prerequisite_symbols": ["fatha", "sukoon"],
    "suitable_types": ["buildup", "free_reading"],
    "skill_buckets": ["connected_decoding"],
    "letter_breakdown": [
      { "letter_id": 27, "position": "initial", "diacritical": "fatha", "tajweed_rules": [] },
      { "letter_id": 23, "position": "medial", "diacritical": "fatha", "tajweed_rules": [] },
      { "letter_id": 24, "position": "final", "diacritical": "sukoon", "tajweed_rules": [] }
    ]
  },
  {
    "arabic_text": "\u064a\u064e\u0643\u064f\u0646",
    "arabic_plain": "\u064a\u0643\u0646",
    "transliteration": "yakun",
    "english_meaning": "there is",
    "root_word": "\u0643\u0648\u0646",
    "surah_number": 112,
    "ayah_number": 4,
    "word_position": 2,
    "quran_frequency": 200,
    "min_phase": 5,
    "difficulty_tier": 2,
    "prerequisite_letter_ids": [28, 22, 25],
    "prerequisite_symbols": ["fatha", "damma", "sukoon"],
    "suitable_types": ["buildup", "free_reading"],
    "skill_buckets": ["connected_decoding"],
    "letter_breakdown": [
      { "letter_id": 28, "position": "initial", "diacritical": "fatha", "tajweed_rules": [] },
      { "letter_id": 22, "position": "medial", "diacritical": "damma", "tajweed_rules": [] },
      { "letter_id": 25, "position": "final", "diacritical": "sukoon", "tajweed_rules": [] }
    ]
  },
  {
    "arabic_text": "\u0644\u0651\u064e\u0647\u064f",
    "arabic_plain": "\u0644\u0647",
    "transliteration": "lahu",
    "english_meaning": "for Him",
    "root_word": null,
    "surah_number": 112,
    "ayah_number": 4,
    "word_position": 3,
    "quran_frequency": 1300,
    "min_phase": 6,
    "difficulty_tier": 2,
    "prerequisite_letter_ids": [23, 26],
    "prerequisite_symbols": ["shaddah", "fatha", "damma"],
    "suitable_types": ["buildup", "free_reading"],
    "skill_buckets": ["connected_decoding"],
    "letter_breakdown": [
      { "letter_id": 23, "position": "initial", "diacritical": "shaddah_fatha", "tajweed_rules": ["shaddah"] },
      { "letter_id": 26, "position": "final", "diacritical": "damma", "tajweed_rules": [] }
    ]
  },
  {
    "arabic_text": "\u0643\u064f\u0641\u064f\u0648\u064b\u0627",
    "arabic_plain": "\u0643\u0641\u0648\u0627",
    "transliteration": "kufuwan",
    "english_meaning": "equivalent",
    "root_word": "\u0643\u0641\u0623",
    "surah_number": 112,
    "ayah_number": 4,
    "word_position": 4,
    "quran_frequency": 2,
    "min_phase": 6,
    "difficulty_tier": 4,
    "prerequisite_letter_ids": [22, 20, 27, 1],
    "prerequisite_symbols": ["damma", "tanwin_damm"],
    "suitable_types": ["free_reading"],
    "skill_buckets": ["connected_decoding", "madd_reading"],
    "letter_breakdown": [
      { "letter_id": 22, "position": "initial", "diacritical": "damma", "tajweed_rules": [] },
      { "letter_id": 20, "position": "medial", "diacritical": "damma", "tajweed_rules": [] },
      { "letter_id": 27, "position": "medial", "diacritical": "tanwin_damm", "tajweed_rules": ["madd_iwad"] },
      { "letter_id": 1, "position": "final", "diacritical": null, "tajweed_rules": [] }
    ]
  },
  {
    "arabic_text": "\u0623\u064e\u062d\u064e\u062f\u064c",
    "arabic_plain": "\u0627\u062d\u062f",
    "transliteration": "ahadun",
    "english_meaning": "one",
    "root_word": "\u0627\u062d\u062f",
    "surah_number": 112,
    "ayah_number": 4,
    "word_position": 5,
    "quran_frequency": 86,
    "min_phase": 6,
    "difficulty_tier": 3,
    "prerequisite_letter_ids": [1, 6, 8],
    "prerequisite_symbols": ["fatha", "tanwin_damm", "hamzah"],
    "suitable_types": ["free_reading"],
    "skill_buckets": ["connected_decoding", "hamzah_reading"],
    "letter_breakdown": [
      { "letter_id": 1, "position": "initial", "diacritical": "fatha", "tajweed_rules": ["hamzah_above"] },
      { "letter_id": 6, "position": "medial", "diacritical": "fatha", "tajweed_rules": [] },
      { "letter_id": 8, "position": "final", "diacritical": "tanwin_damm", "tajweed_rules": [] }
    ]
  }
]
